MANIFEST.in
setup.py
extra_files/__init__.py
extra_files/admin.py
extra_files/forms.py
extra_files/models.py
extra_files/navigation.py
extra_files/tables.py
extra_files/template_content.py
extra_files/urls.py
extra_files/views.py
extra_files/migrations/0001_initial.py
extra_files/migrations/__init__.py
extra_files/templates/extra_files/index.html
extra_files/templates/extra_files/upload.html
extra_files/templates/extra_files/circuits/list.html
netbox_extra_files.egg-info/PKG-INFO
netbox_extra_files.egg-info/SOURCES.txt
netbox_extra_files.egg-info/dependency_links.txt
netbox_extra_files.egg-info/not-zip-safe
netbox_extra_files.egg-info/top_level.txt